pinster/__init__.py
pinster/logger.py
pinster/main.py
pinster/configs/logging.json
pinster-0.1.1.dist-info/METADATA
pinster-0.1.1.dist-info/WHEEL
pinster-0.1.1.dist-info/entry_points.txt
pinster-0.1.1.dist-info/licenses/LICENSE
pinster-0.1.1.dist-info/RECORD
