Metadata-Version: 2.4
Name: pinster
Version: 0.1.1
Summary: Hitster CLI clone
Author: pin
License-File: LICENSE
Requires-Python: >=3.13
Requires-Dist: platformdirs>=4.3.6
Requires-Dist: python-json-logger>=3.2.1
Requires-Dist: spotipy>=2.25.0
Requires-Dist: typer>=0.15.1
